README.md
setup.py
jdp/__init__.py
jdp/client.py
jdp/server.py
jdp.egg-info/PKG-INFO
jdp.egg-info/SOURCES.txt
jdp.egg-info/dependency_links.txt
jdp.egg-info/top_level.txt