Metadata-Version: 2.1
Name: jdp
Version: 0.1.0
Summary: JSON Datagram Protocol
Home-page: https://github.com/ideoforms/python-jdp
Author: Daniel Jones
Author-email: dan-code@erase.net
License: UNKNOWN
Keywords: networking,json,communications,udp
Platform: UNKNOWN
Classifier: Topic :: System :: Networking
Classifier: Topic :: Communications
Classifier: Development Status :: 3 - Alpha
Classifier: Intended Audience :: Developers
